Working_HDMI_passthrough.srcs/sources_1/new/nbit_shiftreg.v
`timescale 1ns / 1ps
//////////////////////////////////////////////////////////////////////////////////
// Company: 
// Engineer: 
// 
// Create Date: 08.06.2021 10:54:00
// Design Name: 
// Module Name: nbit_shiftreg
// Project Name: 
// Target Devices: 
// Tool Versions: 
// Description: 
// 
// Dependencies: 
// 
// Revision:
// Revision 0.01 - File Created
// Additional Comments:
// 
//////////////////////////////////////////////////////////////////////////////////


module nbit_shiftreg#(parameter MSB=4) (  input d,                      // Declare input for data to the first flop in the shift register
                                        input clk,                    // Declare input for clock to all flops in the shift register
                                        input en,                     // Declare input for enable to switch the shift register on/off
                                        input dir,                    // Declare input to shift in either left or right direction
                                        input rstn,                   // Declare input to reset the register to a default value
                                        output reg [MSB-1:0] out);    // Declare output to read out the current value of all flops in this register


   // This always block will "always" be triggered on the rising edge of clock
   // Once it enters the block, it will first check to see if reset is 0 and if yes then reset register
   // If no, then check to see if the shift register is enabled
   // If no => maintain previous output. If yes, then shift based on the requested direction
   always @ (posedge clk)
      if (!rstn)
         out <= 0;
      else begin
         if (en)
            case (dir)
               0 :  out <= {out[MSB-2:0], d};
               1 :  out <= {d, out[MSB-1:1]};
            endcase
         else
            out <= out;
      end
endmodule

Working_HDMI_passthrough.srcs/sim_1/new/delay_bus_tb.v
`timescale 1ns / 1ps
//////////////////////////////////////////////////////////////////////////////////
// Company: 
// Engineer: 
// 
// Create Date: 07.06.2021 17:54:53
// Design Name: 
// Module Name: delay_bus_tb
// Project Name: 
// Target Devices: 
// Tool Versions: 
// Description: 
// 
// Dependencies: 
// 
// Revision:
// Revision 0.01 - File Created
// Additional Comments:
// 
//////////////////////////////////////////////////////////////////////////////////


module delay_bus_tb;

   parameter MSB = 4;        // [Optional] Declare a parameter to represent number of bits in shift register
 
   reg data;                  // Declare a variable to drive d-input of design
   reg clk;                   // Declare a variable to drive clock to the design
   reg en;                    // Declare a variable to drive enable to the design
   reg dir;                   // Declare a variable to drive direction of shift registe
   reg rstn;                  // Declare a variable to drive reset to the design
   wire [MSB-1:0] out;        // Declare a wire to capture output from the design
 
   // Instantiate design (16-bit shift register) by passing MSB and connect with TB signals
   nbit_shiftreg  #(MSB) UUT  (  .d (data),
                             .clk (clk),
                             .en (en),
                             .dir (dir),
                             .rstn (rstn),
                             .out (out));
 
   // Generate clock time period = 20ns, freq => 50MHz
   always #10 clk = ~clk;
 
   // Initialize variables to default values at time 0
   initial begin
      clk <= 0;
      en <= 0;
      dir <= 0;
      rstn <= 0;
      data <= 'h1;
   end
 
   // Drive main stimulus to the design to verify if this works
   initial begin
 
      // 1. Apply reset and deassert reset after some time
      rstn <= 0;
      #20 rstn <= 1;
          en <= 1;
 
    // 2. For 7 clocks, drive alternate values to data pin
      repeat (7) @ (posedge clk)
         data <= ~data;
 
     // 4. Shift direction and drive alternate value to data pin for another 7 clocks
      #10 dir <= 1;
      repeat (7) @ (posedge clk)
         data <= ~data;
 
      // 5. Drive nothing for next 7 clocks, allow shift register to simply shift based on dir
      repeat (7) @ (posedge clk);
     
      // 6. Finish the simulation
      $finish;
   end
 
   // Monitor values of these variables and print them into the logfile for debug
   initial begin
      $monitor ("rstn=%0b data=%b, en=%0b, dir=%0b, out=%b", rstn, data, en, dir, out);
  	  $dumpvars;
     $dumpfile("dump.vcd");
   end
endmodule

Working_HDMI_passthrough.sim/sim_1/behav/xsim/dump.vcd
$date
   Wed Jun  9 15:21:39 2021
$end
$version
  2020.2
$end
$timescale
  1ps
$end
$scope module delay_bus_tb $end
$var reg 1 ! data $end
$var reg 1 " clk $end
$var reg 1 # en $end
$var reg 1 $ dir $end
$var reg 1 % rstn $end
$var wire 4 & out [3:0] $end
$var parameter 32 ' MSB [31:0] $end
$scope module UUT $end
$var wire 1 ( d $end
$var wire 1 ) clk $end
$var wire 1 * en $end
$var wire 1 + dir $end
$var wire 1 , rstn $end
$var reg 4 - out [3:0] $end
$var parameter 32 . MSB [31:0] $end
$upscope $end
$upscope $end
$enddefinitions $end
#0
$dumpvars
1!
0"
0#
0$
0%
bx &
b100 '
1(
0)
0*
0+
0,
bx -
b100 .
$end
#10000
1"
b0 &
1)
b0 -
#20000
0"
1#
1%
0)
1*
1,
#30000
0!
1"
b1 &
0(
1)
b1 -
#40000
0"
0)
#50000
1!
1"
b10 &
1(
1)
b10 -
#60000
0"
0)
#70000
0!
1"
b101 &
0(
1)
b101 -
#80000
0"
0)
#90000
1!
1"
b1010 &
1(
1)
b1010 -
#100000
0"
0)
#110000
0!
1"
b101 &
0(
1)
b101 -
#120000
0"
0)
#130000
1!
1"
b1010 &
1(
1)
b1010 -
#140000
0"
0)
#150000
0!
1"
b101 &
0(
1)
b101 -
#160000
0"
1$
0)
1+
#170000
1!
1"
b10 &
1(
1)
b10 -
#180000
0"
0)
#190000
0!
1"
b1001 &
0(
1)
b1001 -
#200000
0"
0)
#210000
1!
1"
b100 &
1(
1)
b100 -
#220000
0"
0)
#230000
0!
1"
b1010 &
0(
1)
b1010 -
#240000
0"
0)
#250000
1!
1"
b101 &
1(
1)
b101 -
#260000
0"
0)
#270000
0!
1"
b1010 &
0(
1)
b1010 -
#280000
0"
0)
#290000
1!
1"
b101 &
1(
1)
b101 -
#300000
0"
0)
#310000
1"
b1010 &
1)
b1010 -
#320000
0"
0)
#330000
1"
b1101 &
1)
b1101 -
#340000
0"
0)
#350000
1"
b1110 &
1)
b1110 -
#360000
0"
0)
#370000
1"
b1111 &
1)
b1111 -
#380000
0"
0)
#390000
1"
1)
b1111 -
#400000
0"
0)
#410000
1"
1)
b1111 -
